cmd2func/__init__.py
cmd2func/cmd.py
cmd2func/config.py
cmd2func/core.py
cmd2func/runner.py
cmd2func/utils.py
cmd2func-0.2.1.dist-info/LICENSE
cmd2func-0.2.1.dist-info/METADATA
cmd2func-0.2.1.dist-info/WHEEL
cmd2func-0.2.1.dist-info/top_level.txt
cmd2func-0.2.1.dist-info/RECORD
